views_schema/__init__.py
views_schema/base_data_retriever.py
views_schema/docs.py
views_schema/generic.py
views_schema/models.py
views_schema/partitioning.py
views_schema/queryset_manager.py
views_schema/runs.py
views_schema/viewser.py
views_schema-2.3.3.dist-info/LICENSE
views_schema-2.3.3.dist-info/METADATA
views_schema-2.3.3.dist-info/WHEEL
views_schema-2.3.3.dist-info/RECORD
